calnexus/__init__.py
calnexus/app.py
calnexus/demo.py
calnexus-0.1.0.dist-info/WHEEL
calnexus-0.1.0.dist-info/METADATA
calnexus-0.1.0.dist-info/RECORD
