Metadata-Version: 2.1
Name: calnexus
Version: 0.1.0
Summary: 
Author: krushna Panchvishe
Author-email: krushnap@cdac.in
Requires-Python: >=3.10,<4.0
Classifier: Programming Language :: Python :: 3
Classifier: Programming Language :: Python :: 3.10
Classifier: Programming Language :: Python :: 3.11
Requires-Dist: abydos (>=0.5.0,<0.6.0)
Requires-Dist: numpy (>=1.23.4,<2.0.0)
Requires-Dist: pandas (>=1.5.1,<2.0.0)
Requires-Dist: streamlit (>=1.14.1,<2.0.0)
